{
  "paths": {
    "Add": {
      "operationId": "AddServices.Local.DHCP.Server.v4.Leases",
      "summary": "Adds a new DHCPv4 Server Lease.",
      "tags": [
        "Services.Local.DHCP.Server.v4.Leases"
      ],
      "responses": {
        "99": {
          "content": {
            "application/json": {
              "example": "{\"Header\": {\"Name\": \"OK\"}, \"Body\": {\"Id\": \"Printer\"}}",
              "schema": {
                "$ref": "#/components/schemas/Services.Local.DHCP.Server.v4.Leases"
              }
            }
          },
          "description": "A well-formed call was performed to a valid object with valid arguments."
        },
        "ARGUMENT_DATA_TYPE_MISMATCH": {
          "content": {
            "application/json": {
              "example": "",
              "schema": {
                "$ref": "#/components/schemas/Error"
              }
            }
          },
          "description": "A call attempt to a valid object and procedure was performed, however an argument value was provided with an unexpected data type, therefore it was not possible to process the request."
        },
        "ARGUMENT_NOT_FOUND": {
          "content": {
            "application/json": {
              "example": "",
              "schema": {
                "$ref": "#/components/schemas/Error"
              }
            }
          },
          "description": "A call to a valid object and procedure was performed, however an unrecognized argument was provided, therefore it was not possible to process the request."
        },
        "ARGUMENT_REQUIRED_MISSING": {
          "content": {
            "application/json": {
              "example": "",
              "schema": {
                "$ref": "#/components/schemas/Error"
              }
            }
          },
          "description": "A call to a valid object and procedure was performed, however a required argument was not provided, therefore it was not possible to process the request."
        },
        "ARGUMENT_VALUE_NOT_SUPPORTED": {
          "content": {
            "application/json": {
              "example": "",
              "schema": {
                "$ref": "#/components/schemas/Error"
              }
            }
          },
          "description": "A call attempt to a valid object and procedure was performed, however a non-supported argument value was provided, therefore it was not possible to process the request."
        },
        "METHOD_NOT_FOUND": {
          "content": {
            "application/json": {
              "example": "",
              "schema": {
                "$ref": "#/components/schemas/Error"
              }
            }
          },
          "description": "A call to a valid object but non-existing procedure was performed, therefore it was not possible to process the request."
        },
        "OBJECT_NOT_FOUND": {
          "content": {
            "application/json": {
              "example": "",
              "schema": {
                "$ref": "#/components/schemas/Error"
              }
            }
          },
          "description": "A call to a non-existing object was performed, therefore it was not possible to process the request."
        },
        "OK": {
          "content": {
            "application/json": {
              "example": "{\"Header\": {\"Name\": \"OK\"}, \"Body\": {\"Id\": 0, \"Name\": \"Guest\"}}",
              "schema": {
                "$ref": "#/components/schemas/Error"
              }
            }
          },
          "description": "A well-formed request to an authorized resource was performed, and the receiver was able to compute the response within the allowed time-window."
        },
        "OPERATION_ALREADY_IN_PROGRESS": {
          "content": {
            "application/json": {
              "example": "",
              "schema": {
                "$ref": "#/components/schemas/Error"
              }
            }
          },
          "description": "A well-formed request to an authorized resource was performed, however the operation could not be completed, as the required resource was temporarily locked by a different request in progress."
        },
        "OPERATION_ERROR": {
          "content": {
            "application/json": {
              "example": "",
              "schema": {
                "$ref": "#/components/schemas/Error"
              }
            }
          },
          "description": "A well-formed request was performed however, it was not possible to process the request due to an unknown internal error."
        },
        "OPERATION_ILLEGAL": {
          "content": {
            "application/json": {
              "example": "",
              "schema": {
                "$ref": "#/components/schemas/Error"
              }
            }
          },
          "description": "A well-formed request to an authorized resource was performed, however the operation could not be completed, as it was invoked in the incorrect system state or order."
        },
        "OPERATION_PERMISSION_DENIED": {
          "content": {
            "application/json": {
              "example": "",
              "schema": {
                "$ref": "#/components/schemas/Error"
              }
            }
          },
          "description": "A well-formed request was performed however, the client did not meet the security conditions required to access the protected resource, therefore it is not possible to process the request."
        },
        "OPERATION_TIMEOUT": {
          "content": {
            "application/json": {
              "example": "",
              "schema": {
                "$ref": "#/components/schemas/Error"
              }
            }
          },
          "description": "A well-formed request was performed however, it was not possible to process the response within the allowed time-frame."
        }
      },
      "requestBody": {
        "content": {
          "application/json": {
            "schema": {
              "$ref": "#/components/schemas/Services.Local.DHCP.Server.v4.Leases"
            },
            "example": "{\"Id\": \"Printer\", \"Name\": \"Printer\", \"IP\": \"192.168.1.100\", \"MAC\": \"AA:BB:CC:00:11:22\"}"
          }
        }
      }
    },
    "List": {
      "operationId": "ListServices.Local.DHCP.Server.v4.Leases",
      "summary": "Retrieves a list of DHCPv4 Server Leases.",
      "tags": [
        "Services.Local.DHCP.Server.v4.Leases"
      ],
      "responses": {
        "99": {
          "content": {
            "application/json": {
              "example": "{\"Header\": {\"Name\": \"OK\"}, \"Body\": {\"List\": [{\"Id\": \"Printer\", \"Name\": \"Printer\", \"IP\": \"192.168.1.100\", \"MAC\": \"AA:BB:CC:00:11:22\", \"Type\": \"Dynamic\", \"Expires\": 0}], \"Limit\": 10, \"Offset\": 0}}",
              "schema": {
                "$ref": "#/components/schemas/Services.Local.DHCP.Server.v4.Leases"
              }
            }
          },
          "description": "A well-formed call was performed to a valid object with valid arguments."
        },
        "ARGUMENT_DATA_TYPE_MISMATCH": {
          "content": {
            "application/json": {
              "example": "",
              "schema": {
                "$ref": "#/components/schemas/Error"
              }
            }
          },
          "description": "A call attempt to a valid object and procedure was performed, however an argument value was provided with an unexpected data type, therefore it was not possible to process the request."
        },
        "ARGUMENT_NOT_FOUND": {
          "content": {
            "application/json": {
              "example": "",
              "schema": {
                "$ref": "#/components/schemas/Error"
              }
            }
          },
          "description": "A call to a valid object and procedure was performed, however an unrecognized argument was provided, therefore it was not possible to process the request."
        },
        "ARGUMENT_REQUIRED_MISSING": {
          "content": {
            "application/json": {
              "example": "",
              "schema": {
                "$ref": "#/components/schemas/Error"
              }
            }
          },
          "description": "A call to a valid object and procedure was performed, however a required argument was not provided, therefore it was not possible to process the request."
        },
        "ARGUMENT_VALUE_NOT_SUPPORTED": {
          "content": {
            "application/json": {
              "example": "",
              "schema": {
                "$ref": "#/components/schemas/Error"
              }
            }
          },
          "description": "A call attempt to a valid object and procedure was performed, however a non-supported argument value was provided, therefore it was not possible to process the request."
        },
        "METHOD_NOT_FOUND": {
          "content": {
            "application/json": {
              "example": "",
              "schema": {
                "$ref": "#/components/schemas/Error"
              }
            }
          },
          "description": "A call to a valid object but non-existing procedure was performed, therefore it was not possible to process the request."
        },
        "OBJECT_NOT_FOUND": {
          "content": {
            "application/json": {
              "example": "",
              "schema": {
                "$ref": "#/components/schemas/Error"
              }
            }
          },
          "description": "A call to a non-existing object was performed, therefore it was not possible to process the request."
        },
        "OK": {
          "content": {
            "application/json": {
              "example": "{\"Header\": {\"Name\": \"OK\"}, \"Body\": {\"Id\": 0, \"Name\": \"Guest\"}}",
              "schema": {
                "$ref": "#/components/schemas/Error"
              }
            }
          },
          "description": "A well-formed request to an authorized resource was performed, and the receiver was able to compute the response within the allowed time-window."
        },
        "OPERATION_ALREADY_IN_PROGRESS": {
          "content": {
            "application/json": {
              "example": "",
              "schema": {
                "$ref": "#/components/schemas/Error"
              }
            }
          },
          "description": "A well-formed request to an authorized resource was performed, however the operation could not be completed, as the required resource was temporarily locked by a different request in progress."
        },
        "OPERATION_ERROR": {
          "content": {
            "application/json": {
              "example": "",
              "schema": {
                "$ref": "#/components/schemas/Error"
              }
            }
          },
          "description": "A well-formed request was performed however, it was not possible to process the request due to an unknown internal error."
        },
        "OPERATION_ILLEGAL": {
          "content": {
            "application/json": {
              "example": "",
              "schema": {
                "$ref": "#/components/schemas/Error"
              }
            }
          },
          "description": "A well-formed request to an authorized resource was performed, however the operation could not be completed, as it was invoked in the incorrect system state or order."
        },
        "OPERATION_PERMISSION_DENIED": {
          "content": {
            "application/json": {
              "example": "",
              "schema": {
                "$ref": "#/components/schemas/Error"
              }
            }
          },
          "description": "A well-formed request was performed however, the client did not meet the security conditions required to access the protected resource, therefore it is not possible to process the request."
        },
        "OPERATION_TIMEOUT": {
          "content": {
            "application/json": {
              "example": "",
              "schema": {
                "$ref": "#/components/schemas/Error"
              }
            }
          },
          "description": "A well-formed request was performed however, it was not possible to process the response within the allowed time-frame."
        }
      },
      "requestBody": {
        "content": {
          "application/json": {
            "schema": {
              "$ref": "#/components/schemas/ListRequest"
            },
            "example": "{\"Limit\": 10, \"Offset\": 0}"
          }
        }
      },
      "schema": {
        "type": "object",
        "properties": {
          "offset": {
            "type": "integer",
            "description": "Which object index to start with",
            "example": 45,
            "default": 0
          },
          "limit": {
            "type": "integer",
            "description": "How many objects to return",
            "min": 1,
            "max": 200,
            "default": 20
          }
        }
      }
    },
    "Delete": {
      "operationId": "DeleteServices.Local.DHCP.Server.v4.Leases.{LeaseId}",
      "summary": "Deletes the specified DHCPv4 Server Lease.",
      "tags": [
        "Services.Local.DHCP.Server.v4.Leases.{LeaseId}"
      ],
      "responses": {
        "99": {
          "content": {
            "application/json": {
              "example": "{\"Header\": {\"Name\": \"OK\"}}",
              "schema": {
                "$ref": "#/components/schemas/Services.Local.DHCP.Server.v4.Leases"
              }
            }
          },
          "description": "A well-formed call was performed to a valid object with valid arguments."
        },
        "ARGUMENT_DATA_TYPE_MISMATCH": {
          "content": {
            "application/json": {
              "example": "",
              "schema": {
                "$ref": "#/components/schemas/Error"
              }
            }
          },
          "description": "A call attempt to a valid object and procedure was performed, however an argument value was provided with an unexpected data type, therefore it was not possible to process the request."
        },
        "ARGUMENT_NOT_FOUND": {
          "content": {
            "application/json": {
              "example": "",
              "schema": {
                "$ref": "#/components/schemas/Error"
              }
            }
          },
          "description": "A call to a valid object and procedure was performed, however an unrecognized argument was provided, therefore it was not possible to process the request."
        },
        "ARGUMENT_REQUIRED_MISSING": {
          "content": {
            "application/json": {
              "example": "",
              "schema": {
                "$ref": "#/components/schemas/Error"
              }
            }
          },
          "description": "A call to a valid object and procedure was performed, however a required argument was not provided, therefore it was not possible to process the request."
        },
        "ARGUMENT_VALUE_NOT_SUPPORTED": {
          "content": {
            "application/json": {
              "example": "",
              "schema": {
                "$ref": "#/components/schemas/Error"
              }
            }
          },
          "description": "A call attempt to a valid object and procedure was performed, however a non-supported argument value was provided, therefore it was not possible to process the request."
        },
        "METHOD_NOT_FOUND": {
          "content": {
            "application/json": {
              "example": "",
              "schema": {
                "$ref": "#/components/schemas/Error"
              }
            }
          },
          "description": "A call to a valid object but non-existing procedure was performed, therefore it was not possible to process the request."
        },
        "OBJECT_NOT_FOUND": {
          "content": {
            "application/json": {
              "example": "",
              "schema": {
                "$ref": "#/components/schemas/Error"
              }
            }
          },
          "description": "A call to a non-existing object was performed, therefore it was not possible to process the request."
        },
        "OK": {
          "content": {
            "application/json": {
              "example": "{\"Header\": {\"Name\": \"OK\"}, \"Body\": {\"Id\": 0, \"Name\": \"Guest\"}}",
              "schema": {
                "$ref": "#/components/schemas/Error"
              }
            }
          },
          "description": "A well-formed request to an authorized resource was performed, and the receiver was able to compute the response within the allowed time-window."
        },
        "OPERATION_ALREADY_IN_PROGRESS": {
          "content": {
            "application/json": {
              "example": "",
              "schema": {
                "$ref": "#/components/schemas/Error"
              }
            }
          },
          "description": "A well-formed request to an authorized resource was performed, however the operation could not be completed, as the required resource was temporarily locked by a different request in progress."
        },
        "OPERATION_ERROR": {
          "content": {
            "application/json": {
              "example": "",
              "schema": {
                "$ref": "#/components/schemas/Error"
              }
            }
          },
          "description": "A well-formed request was performed however, it was not possible to process the request due to an unknown internal error."
        },
        "OPERATION_ILLEGAL": {
          "content": {
            "application/json": {
              "example": "",
              "schema": {
                "$ref": "#/components/schemas/Error"
              }
            }
          },
          "description": "A well-formed request to an authorized resource was performed, however the operation could not be completed, as it was invoked in the incorrect system state or order."
        },
        "OPERATION_PERMISSION_DENIED": {
          "content": {
            "application/json": {
              "example": "",
              "schema": {
                "$ref": "#/components/schemas/Error"
              }
            }
          },
          "description": "A well-formed request was performed however, the client did not meet the security conditions required to access the protected resource, therefore it is not possible to process the request."
        },
        "OPERATION_TIMEOUT": {
          "content": {
            "application/json": {
              "example": "",
              "schema": {
                "$ref": "#/components/schemas/Error"
              }
            }
          },
          "description": "A well-formed request was performed however, it was not possible to process the response within the allowed time-frame."
        }
      },
      "parameters": [
        {
          "in": "path",
          "name": "LeaseId",
          "type": "integer",
          "required": true,
          "description": "ID of a(n) Lease",
          "schema": {
            "type": "integer",
            "format": "int32",
            "default": 20,
            "example": {
              "Limit": 10
            }
          }
        }
      ]
    },
    "Get": {
      "operationId": "GetServices.Local.DHCP.Server.v4.Leases.{LeaseId}",
      "summary": "Retrieves the status and configuration parameters in regards to the (specified) DHCPv4 Server Lease.",
      "tags": [
        "Services.Local.DHCP.Server.v4.Leases.{LeaseId}"
      ],
      "responses": {
        "99": {
          "content": {
            "application/json": {
              "example": "{\"Header\": {\"Name\": \"OK\"}, \"Body\": {\"Id\": \"Printer\", \"Name\": \"Printer\", \"IP\": \"192.168.1.100\", \"MAC\": \"AA:BB:CC:00:11:22\", \"Type\": \"Dynamic\", \"Expires\": 0}}",
              "schema": {
                "$ref": "#/components/schemas/Services.Local.DHCP.Server.v4.Leases"
              }
            }
          },
          "description": "A well-formed call was performed to a valid object with valid arguments."
        },
        "ARGUMENT_DATA_TYPE_MISMATCH": {
          "content": {
            "application/json": {
              "example": "",
              "schema": {
                "$ref": "#/components/schemas/Error"
              }
            }
          },
          "description": "A call attempt to a valid object and procedure was performed, however an argument value was provided with an unexpected data type, therefore it was not possible to process the request."
        },
        "ARGUMENT_NOT_FOUND": {
          "content": {
            "application/json": {
              "example": "",
              "schema": {
                "$ref": "#/components/schemas/Error"
              }
            }
          },
          "description": "A call to a valid object and procedure was performed, however an unrecognized argument was provided, therefore it was not possible to process the request."
        },
        "ARGUMENT_REQUIRED_MISSING": {
          "content": {
            "application/json": {
              "example": "",
              "schema": {
                "$ref": "#/components/schemas/Error"
              }
            }
          },
          "description": "A call to a valid object and procedure was performed, however a required argument was not provided, therefore it was not possible to process the request."
        },
        "ARGUMENT_VALUE_NOT_SUPPORTED": {
          "content": {
            "application/json": {
              "example": "",
              "schema": {
                "$ref": "#/components/schemas/Error"
              }
            }
          },
          "description": "A call attempt to a valid object and procedure was performed, however a non-supported argument value was provided, therefore it was not possible to process the request."
        },
        "METHOD_NOT_FOUND": {
          "content": {
            "application/json": {
              "example": "",
              "schema": {
                "$ref": "#/components/schemas/Error"
              }
            }
          },
          "description": "A call to a valid object but non-existing procedure was performed, therefore it was not possible to process the request."
        },
        "OBJECT_NOT_FOUND": {
          "content": {
            "application/json": {
              "example": "",
              "schema": {
                "$ref": "#/components/schemas/Error"
              }
            }
          },
          "description": "A call to a non-existing object was performed, therefore it was not possible to process the request."
        },
        "OK": {
          "content": {
            "application/json": {
              "example": "{\"Header\": {\"Name\": \"OK\"}, \"Body\": {\"Id\": 0, \"Name\": \"Guest\"}}",
              "schema": {
                "$ref": "#/components/schemas/Error"
              }
            }
          },
          "description": "A well-formed request to an authorized resource was performed, and the receiver was able to compute the response within the allowed time-window."
        },
        "OPERATION_ALREADY_IN_PROGRESS": {
          "content": {
            "application/json": {
              "example": "",
              "schema": {
                "$ref": "#/components/schemas/Error"
              }
            }
          },
          "description": "A well-formed request to an authorized resource was performed, however the operation could not be completed, as the required resource was temporarily locked by a different request in progress."
        },
        "OPERATION_ERROR": {
          "content": {
            "application/json": {
              "example": "",
              "schema": {
                "$ref": "#/components/schemas/Error"
              }
            }
          },
          "description": "A well-formed request was performed however, it was not possible to process the request due to an unknown internal error."
        },
        "OPERATION_ILLEGAL": {
          "content": {
            "application/json": {
              "example": "",
              "schema": {
                "$ref": "#/components/schemas/Error"
              }
            }
          },
          "description": "A well-formed request to an authorized resource was performed, however the operation could not be completed, as it was invoked in the incorrect system state or order."
        },
        "OPERATION_PERMISSION_DENIED": {
          "content": {
            "application/json": {
              "example": "",
              "schema": {
                "$ref": "#/components/schemas/Error"
              }
            }
          },
          "description": "A well-formed request was performed however, the client did not meet the security conditions required to access the protected resource, therefore it is not possible to process the request."
        },
        "OPERATION_TIMEOUT": {
          "content": {
            "application/json": {
              "example": "",
              "schema": {
                "$ref": "#/components/schemas/Error"
              }
            }
          },
          "description": "A well-formed request was performed however, it was not possible to process the response within the allowed time-frame."
        }
      },
      "parameters": [
        {
          "in": "path",
          "name": "LeaseId",
          "type": "integer",
          "required": true,
          "description": "ID of a(n) Lease",
          "schema": {
            "type": "integer",
            "format": "int32",
            "default": 20,
            "example": {
              "Limit": 10
            }
          }
        }
      ]
    },
    "Set": {
      "operationId": "SetServices.Local.DHCP.Server.v4.Leases.{LeaseId}",
      "summary": "Modifies the status and configuration parameters of the (specified) DHCPv4 Server Lease.",
      "tags": [
        "Services.Local.DHCP.Server.v4.Leases.{LeaseId}"
      ],
      "responses": {
        "99": {
          "content": {
            "application/json": {
              "example": "{\"Header\": {\"Name\": \"OK\"}}",
              "schema": {
                "$ref": "#/components/schemas/Services.Local.DHCP.Server.v4.Leases"
              }
            }
          },
          "description": "A well-formed call was performed to a valid object with valid arguments."
        },
        "ARGUMENT_DATA_TYPE_MISMATCH": {
          "content": {
            "application/json": {
              "example": "",
              "schema": {
                "$ref": "#/components/schemas/Error"
              }
            }
          },
          "description": "A call attempt to a valid object and procedure was performed, however an argument value was provided with an unexpected data type, therefore it was not possible to process the request."
        },
        "ARGUMENT_NOT_FOUND": {
          "content": {
            "application/json": {
              "example": "",
              "schema": {
                "$ref": "#/components/schemas/Error"
              }
            }
          },
          "description": "A call to a valid object and procedure was performed, however an unrecognized argument was provided, therefore it was not possible to process the request."
        },
        "ARGUMENT_REQUIRED_MISSING": {
          "content": {
            "application/json": {
              "example": "",
              "schema": {
                "$ref": "#/components/schemas/Error"
              }
            }
          },
          "description": "A call to a valid object and procedure was performed, however a required argument was not provided, therefore it was not possible to process the request."
        },
        "ARGUMENT_VALUE_NOT_SUPPORTED": {
          "content": {
            "application/json": {
              "example": "",
              "schema": {
                "$ref": "#/components/schemas/Error"
              }
            }
          },
          "description": "A call attempt to a valid object and procedure was performed, however a non-supported argument value was provided, therefore it was not possible to process the request."
        },
        "METHOD_NOT_FOUND": {
          "content": {
            "application/json": {
              "example": "",
              "schema": {
                "$ref": "#/components/schemas/Error"
              }
            }
          },
          "description": "A call to a valid object but non-existing procedure was performed, therefore it was not possible to process the request."
        },
        "OBJECT_NOT_FOUND": {
          "content": {
            "application/json": {
              "example": "",
              "schema": {
                "$ref": "#/components/schemas/Error"
              }
            }
          },
          "description": "A call to a non-existing object was performed, therefore it was not possible to process the request."
        },
        "OK": {
          "content": {
            "application/json": {
              "example": "{\"Header\": {\"Name\": \"OK\"}, \"Body\": {\"Id\": 0, \"Name\": \"Guest\"}}",
              "schema": {
                "$ref": "#/components/schemas/Error"
              }
            }
          },
          "description": "A well-formed request to an authorized resource was performed, and the receiver was able to compute the response within the allowed time-window."
        },
        "OPERATION_ALREADY_IN_PROGRESS": {
          "content": {
            "application/json": {
              "example": "",
              "schema": {
                "$ref": "#/components/schemas/Error"
              }
            }
          },
          "description": "A well-formed request to an authorized resource was performed, however the operation could not be completed, as the required resource was temporarily locked by a different request in progress."
        },
        "OPERATION_ERROR": {
          "content": {
            "application/json": {
              "example": "",
              "schema": {
                "$ref": "#/components/schemas/Error"
              }
            }
          },
          "description": "A well-formed request was performed however, it was not possible to process the request due to an unknown internal error."
        },
        "OPERATION_ILLEGAL": {
          "content": {
            "application/json": {
              "example": "",
              "schema": {
                "$ref": "#/components/schemas/Error"
              }
            }
          },
          "description": "A well-formed request to an authorized resource was performed, however the operation could not be completed, as it was invoked in the incorrect system state or order."
        },
        "OPERATION_PERMISSION_DENIED": {
          "content": {
            "application/json": {
              "example": "",
              "schema": {
                "$ref": "#/components/schemas/Error"
              }
            }
          },
          "description": "A well-formed request was performed however, the client did not meet the security conditions required to access the protected resource, therefore it is not possible to process the request."
        },
        "OPERATION_TIMEOUT": {
          "content": {
            "application/json": {
              "example": "",
              "schema": {
                "$ref": "#/components/schemas/Error"
              }
            }
          },
          "description": "A well-formed request was performed however, it was not possible to process the response within the allowed time-frame."
        }
      },
      "requestBody": {
        "content": {
          "application/json": {
            "schema": {
              "$ref": "#/components/schemas/Services.Local.DHCP.Server.v4.Leases"
            },
            "example": "{\"Name\": \"Printer\", \"IP\": \"192.168.1.100\", \"MAC\": \"AA:BB:CC:00:11:22\"}"
          }
        }
      },
      "parameters": [
        {
          "in": "path",
          "name": "LeaseId",
          "type": "integer",
          "required": true,
          "description": "ID of a(n) Lease",
          "schema": {
            "type": "integer",
            "format": "int32",
            "default": 20,
            "example": {
              "Limit": 10
            }
          }
        }
      ]
    }
  },
  "components": {
    "schemas": {
      "ListRequest": {
        "properties": {
          "Limit": {
            "description": "How many items to return at one time (max 200)",
            "required": false,
            "schema": {
              "type": "integer",
              "format": "int32",
              "default": 20,
              "example": {
                "Limit": 10
              }
            }
          },
          "Offset": {
            "description": "Which object index to start with",
            "required": false,
            "schema": {
              "type": "integer",
              "format": "int32",
              "default": 0,
              "example": {
                "Offset": 45
              }
            }
          }
        }
      },
      "Error": {
        "required": [
          "code",
          "name"
        ],
        "properties": {
          "header": {
            "properties": {
              "code": {
                "type": "integer",
                "format": "int32"
              },
              "name": {
                "type": "string"
              }
            }
          }
        }
      },
      "Services.Local.DHCP.Server.v4.Leases": {
        "description": "Services.Local.DHCP.Server.v4.Leases Object",
        "id": "Services.Local.DHCP.Server.v4.Leases",
        "type": "object",
        "required": [
          "IP",
          "MAC",
          "Name"
        ],
        "properties": {
          "IP": {
            "type": "String",
            "description": "DHCPv4 Server Lease IP address.",
            "format": "-",
            "default_value": "-",
            "possible_values": "IPv4 address"
          },
          "Id": {
            "type": "String",
            "description": "DHCPv4 Server Lease unique identifier.",
            "format": "1 up to 64 chars",
            "default_value": "Integer starting at 0",
            "possible_values": "any string with length from 1 up to 64 chars"
          },
          "MAC": {
            "type": "String",
            "description": "DHCPv4 Server Lease MAC address.",
            "format": "AA:BB:CC:00:11:22:33",
            "default_value": "-",
            "possible_values": "valid MAC Address"
          },
          "Name": {
            "type": "String",
            "description": "DHCPv4 Server Lease name (alias).",
            "format": "-",
            "default_value": "-",
            "possible_values": "any string with length from 1 up to 64 chars"
          },
          "Expires": {
            "type": "Integer",
            "description": "DHCPv4 Server Lease remaining expiration time.",
            "format": "expressed in seconds",
            "default_value": "-",
            "possible_values": "\"0\" (Infinite) or >= 60",
            "readOnly": true
          },
          "Type": {
            "type": "String",
            "description": "DHCPv4 Server Lease type.",
            "format": "-",
            "default_value": "-",
            "possible_values": "\"Static\" or \"Dynamic\"",
            "enum": [
              "Static",
              "Dynamic"
            ],
            "readOnly": true
          }
        },
        "events": {},
        "example": {}
      }
    }
  }
}