{
  "paths": {
    "System.Buttons.List": {
      "operationId": "System.Buttons.List",
      "summary": "Retrieves a list of Buttons.",
      "tags": [
        "System.Buttons"
      ],
      "responses": {
        "ARGUMENT_DATA_TYPE_MISMATCH": {
          "description": "A call attempt to a valid object and procedure was performed, however an argument value was provided with an unexpected data type, therefore it was not possible to process the request.",
          "raised_by": "Micro-Service",
          "content": {
            "application/json": {
              "example": "{\"Header\": {\"Name\": \"ARGUMENT_DATA_TYPE_MISMATCH\", \"Description\": \"Unable to process the request because the value provided on the \\u2018Enabled\\u2019 field is not a valid Boolean.\"}}",
              "schema": {
                "$ref": "#/components/schemas/Response"
              }
            }
          }
        },
        "ARGUMENT_NOT_FOUND": {
          "description": "A call to a valid object and procedure was performed, however an unrecognized argument was provided, therefore it was not possible to process the request.",
          "raised_by": "Micro-Service",
          "content": {
            "application/json": {
              "example": "{\"Header\": {\"Name\": \"ARGUMENT_NOT_FOUND\", \"Description\": \"Unable to process the request because 'Enabled' is not a valid argument.\"}}",
              "schema": {
                "$ref": "#/components/schemas/Response"
              }
            }
          }
        },
        "ARGUMENT_REQUIRED_MISSING": {
          "description": "A call to a valid object and procedure was performed, however a required argument was not provided, therefore it was not possible to process the request.",
          "raised_by": "Micro-Service",
          "content": {
            "application/json": {
              "example": "{\"Header\": {\"Name\": \"ARGUMENT_REQUIRED_MISSING\", \"Description\": \"Unable to process the request because the 'Enabled' field was not provided.\"}}",
              "schema": {
                "$ref": "#/components/schemas/Response"
              }
            }
          }
        },
        "ARGUMENT_VALUE_NOT_SUPPORTED": {
          "description": "A call attempt to a valid object and procedure was performed, however a non-supported argument value was provided, therefore it was not possible to process the request.",
          "raised_by": "Micro-Service",
          "content": {
            "application/json": {
              "example": "{\"Header\": {\"Name\": \"ARGUMENT_VALUE_NOT_SUPPORTED\", \"Description\": \"Unable to process the request because \\u2018Red\\u2019 is not a value supported by the \\u2018Colour\\u2019 field.\"}}",
              "schema": {
                "$ref": "#/components/schemas/Response"
              }
            }
          }
        },
        "METHOD_NOT_FOUND": {
          "description": "A call to a valid object but non-existing procedure was performed, therefore it was not possible to process the request.",
          "raised_by": "IPC Bus",
          "content": {
            "application/json": {
              "example": "{\"Header\": {\"Name\": \"METHOD_NOT_FOUND\", \"Description\": \"Unable to process the request because 'Set' is not a valid method\"}}",
              "schema": {
                "$ref": "#/components/schemas/Response"
              }
            }
          }
        },
        "OBJECT_NOT_FOUND": {
          "description": "A call to a non-existing object was performed, therefore it was not possible to process the request.",
          "raised_by": "IPC Bus",
          "content": {
            "application/json": {
              "example": "{\"Header\": {\"Name\": \"OBJECT_NOT_FOUND\", \"Description\": \"Unable to process the request because 'prpl.Dummy' is not a valid object.\"}}",
              "schema": {
                "$ref": "#/components/schemas/Response"
              }
            }
          }
        },
        "OK": {
          "description": "A well-formed request to an authorized resource was performed, and the receiver was able to compute the response within the allowed time-window.",
          "raised_by": "Micro-Service",
          "content": {
            "application/json": {
              "example": "{\"Header\": {\"Name\": \"OK\"}, \"Body\": {\"List\": [{\"Id\": \"0\", \"Name\": \"Wi-Fi\", \"Enabled\": true, \"Actions\": {\"Click\": {\"Object\": \"Interfaces.Physical.Network.LAN.Wi-Fi.Radios.24GHz\", \"Method\": \"Set\", \"Arguments\": {\"Enabled\": false}}, \"Press\": {\"Object\": \"Services.Local.Wi-Fi.WPS.Pairing\", \"Method\": \"Start\", \"Arguments\": null}}, \"Statistics\": {\"Click\": 0, \"Press\": 0}}], \"Limit\": 10, \"Offset\": 0}}",
              "schema": {
                "allOf": [
                  {
                    "$ref": "#/components/schemas/Response"
                  },
                  {
                    "properties": {
                      "Body": {
                        "properties": {
                          "Limit": {
                            "type": "Integer",
                            "description": "Button maximum number of returned entries.",
                            "format": "-",
                            "default_value": "0",
                            "possible_values": "\"0\" to fetch all entries or positive integer"
                          },
                          "List": {
                            "type": "List",
                            "description": "Button list of entries.",
                            "format": "-",
                            "default_value": "-",
                            "possible_values": "-",
                            "readOnly": true
                          },
                          "Offset": {
                            "type": "Integer",
                            "description": "Button list start offset.",
                            "format": "-",
                            "default_value": "0",
                            "possible_values": "\"0\" to fetch all entries or positive integer"
                          }
                        },
                        "required": []
                      }
                    }
                  }
                ]
              }
            }
          }
        },
        "OPERATION_ALREADY_IN_PROGRESS": {
          "description": "A well-formed request to an authorized resource was performed, however the operation could not be completed, as the required resource was temporarily locked by a different request in progress.",
          "raised_by": "Micro-Service",
          "content": {
            "application/json": {
              "example": "{\"Header\": {\"Name\": \"OPERATION_ALREADY_IN_PROGRESS\", \"Description\": \"Unable to process the request because there is a duplicate operation currently in progress.\"}}",
              "schema": {
                "$ref": "#/components/schemas/Response"
              }
            }
          }
        },
        "OPERATION_ERROR": {
          "description": "A well-formed request was performed however, it was not possible to process the request due to an unknown internal error.",
          "raised_by": "Micro-Service",
          "content": {
            "application/json": {
              "example": "{\"Header\": {\"Name\": \"OPERATION_ERROR\", \"Description\": \"Unable to process the request because there is a configuration error.\"}}",
              "schema": {
                "$ref": "#/components/schemas/Response"
              }
            }
          }
        },
        "OPERATION_ILLEGAL": {
          "description": "A well-formed request to an authorized resource was performed, however the operation could not be completed, as it was invoked in the incorrect system state or order.",
          "raised_by": "Micro-Service",
          "content": {
            "application/json": {
              "example": "{\"Header\": {\"Name\": \"OPERATION_ILLEGAL\", \"Description\": \"Unable to process the request because the 'Stop' procedure can only be invoked after the 'Start' method has been called.\"}}",
              "schema": {
                "$ref": "#/components/schemas/Response"
              }
            }
          }
        },
        "OPERATION_PERMISSION_DENIED": {
          "description": "A well-formed request was performed however, the client did not meet the security conditions required to access the protected resource, therefore it is not possible to process the request.",
          "raised_by": "IPC Bus / Remote Protocol Adapter",
          "content": {
            "application/json": {
              "example": "{\"Header\": {\"Name\": \"OPERATION_PERMISSION_DENIED\", \"Description\": \"Unable to process the request because user \\u2018Admin\\u2019 does not have access privileges to invoke the \\u2018Set\\u2019 procedure on object \\u2018prpl.Dummy\\u2019.\"}}",
              "schema": {
                "$ref": "#/components/schemas/Response"
              }
            }
          }
        },
        "OPERATION_TIMEOUT": {
          "description": "A well-formed request was performed however, it was not possible to process the response within the allowed time-frame.",
          "raised_by": "Micro-Service",
          "content": {
            "application/json": {
              "example": "{\"Header\": {\"Name\": \"OPERATION_TIMEOUT\", \"Description\": \"The operation has been aborted because the service did not respond within the expected 5 seconds time-frame.\"}}",
              "schema": {
                "$ref": "#/components/schemas/Response"
              }
            }
          }
        }
      },
      "requestBody": {
        "content": {
          "application/json": {
            "schema": {
              "properties": {
                "Limit": {
                  "type": "Integer",
                  "description": "Button maximum number of returned entries.",
                  "format": "-",
                  "default_value": "0",
                  "possible_values": "\"0\" to fetch all entries or positive integer"
                },
                "Offset": {
                  "type": "Integer",
                  "description": "Button list start offset.",
                  "format": "-",
                  "default_value": "0",
                  "possible_values": "\"0\" to fetch all entries or positive integer"
                }
              },
              "required": []
            },
            "example": "{\"Limit\": 10, \"Offset\": 0}"
          }
        }
      },
      "schema": {
        "type": "object",
        "properties": {
          "offset": {
            "type": "integer",
            "description": "Which object index to start with",
            "example": 45,
            "default": 0
          },
          "limit": {
            "type": "integer",
            "description": "How many objects to return",
            "min": 1,
            "max": 200,
            "default": 20
          }
        }
      }
    },
    "System.Buttons.{ButtonId}.Get": {
      "operationId": "System.Buttons.{ButtonId}.Get",
      "summary": "Retrieves the status and configuration parameters in regards to the specified Button.",
      "tags": [
        "System.Buttons.{ButtonId}"
      ],
      "responses": {
        "ARGUMENT_DATA_TYPE_MISMATCH": {
          "description": "A call attempt to a valid object and procedure was performed, however an argument value was provided with an unexpected data type, therefore it was not possible to process the request.",
          "raised_by": "Micro-Service",
          "content": {
            "application/json": {
              "example": "{\"Header\": {\"Name\": \"ARGUMENT_DATA_TYPE_MISMATCH\", \"Description\": \"Unable to process the request because the value provided on the \\u2018Enabled\\u2019 field is not a valid Boolean.\"}}",
              "schema": {
                "$ref": "#/components/schemas/Response"
              }
            }
          }
        },
        "ARGUMENT_NOT_FOUND": {
          "description": "A call to a valid object and procedure was performed, however an unrecognized argument was provided, therefore it was not possible to process the request.",
          "raised_by": "Micro-Service",
          "content": {
            "application/json": {
              "example": "{\"Header\": {\"Name\": \"ARGUMENT_NOT_FOUND\", \"Description\": \"Unable to process the request because 'Enabled' is not a valid argument.\"}}",
              "schema": {
                "$ref": "#/components/schemas/Response"
              }
            }
          }
        },
        "ARGUMENT_REQUIRED_MISSING": {
          "description": "A call to a valid object and procedure was performed, however a required argument was not provided, therefore it was not possible to process the request.",
          "raised_by": "Micro-Service",
          "content": {
            "application/json": {
              "example": "{\"Header\": {\"Name\": \"ARGUMENT_REQUIRED_MISSING\", \"Description\": \"Unable to process the request because the 'Enabled' field was not provided.\"}}",
              "schema": {
                "$ref": "#/components/schemas/Response"
              }
            }
          }
        },
        "ARGUMENT_VALUE_NOT_SUPPORTED": {
          "description": "A call attempt to a valid object and procedure was performed, however a non-supported argument value was provided, therefore it was not possible to process the request.",
          "raised_by": "Micro-Service",
          "content": {
            "application/json": {
              "example": "{\"Header\": {\"Name\": \"ARGUMENT_VALUE_NOT_SUPPORTED\", \"Description\": \"Unable to process the request because \\u2018Red\\u2019 is not a value supported by the \\u2018Colour\\u2019 field.\"}}",
              "schema": {
                "$ref": "#/components/schemas/Response"
              }
            }
          }
        },
        "METHOD_NOT_FOUND": {
          "description": "A call to a valid object but non-existing procedure was performed, therefore it was not possible to process the request.",
          "raised_by": "IPC Bus",
          "content": {
            "application/json": {
              "example": "{\"Header\": {\"Name\": \"METHOD_NOT_FOUND\", \"Description\": \"Unable to process the request because 'Set' is not a valid method\"}}",
              "schema": {
                "$ref": "#/components/schemas/Response"
              }
            }
          }
        },
        "OBJECT_NOT_FOUND": {
          "description": "A call to a non-existing object was performed, therefore it was not possible to process the request.",
          "raised_by": "IPC Bus",
          "content": {
            "application/json": {
              "example": "{\"Header\": {\"Name\": \"OBJECT_NOT_FOUND\", \"Description\": \"Unable to process the request because 'prpl.Dummy' is not a valid object.\"}}",
              "schema": {
                "$ref": "#/components/schemas/Response"
              }
            }
          }
        },
        "OK": {
          "description": "A well-formed request to an authorized resource was performed, and the receiver was able to compute the response within the allowed time-window.",
          "raised_by": "Micro-Service",
          "content": {
            "application/json": {
              "example": "{\"Header\": {\"Name\": \"OK\"}}",
              "schema": {
                "allOf": [
                  {
                    "$ref": "#/components/schemas/Response"
                  },
                  {
                    "properties": {
                      "Body": {
                        "properties": {},
                        "required": []
                      }
                    }
                  }
                ]
              }
            }
          }
        },
        "OPERATION_ALREADY_IN_PROGRESS": {
          "description": "A well-formed request to an authorized resource was performed, however the operation could not be completed, as the required resource was temporarily locked by a different request in progress.",
          "raised_by": "Micro-Service",
          "content": {
            "application/json": {
              "example": "{\"Header\": {\"Name\": \"OPERATION_ALREADY_IN_PROGRESS\", \"Description\": \"Unable to process the request because there is a duplicate operation currently in progress.\"}}",
              "schema": {
                "$ref": "#/components/schemas/Response"
              }
            }
          }
        },
        "OPERATION_ERROR": {
          "description": "A well-formed request was performed however, it was not possible to process the request due to an unknown internal error.",
          "raised_by": "Micro-Service",
          "content": {
            "application/json": {
              "example": "{\"Header\": {\"Name\": \"OPERATION_ERROR\", \"Description\": \"Unable to process the request because there is a configuration error.\"}}",
              "schema": {
                "$ref": "#/components/schemas/Response"
              }
            }
          }
        },
        "OPERATION_ILLEGAL": {
          "description": "A well-formed request to an authorized resource was performed, however the operation could not be completed, as it was invoked in the incorrect system state or order.",
          "raised_by": "Micro-Service",
          "content": {
            "application/json": {
              "example": "{\"Header\": {\"Name\": \"OPERATION_ILLEGAL\", \"Description\": \"Unable to process the request because the 'Stop' procedure can only be invoked after the 'Start' method has been called.\"}}",
              "schema": {
                "$ref": "#/components/schemas/Response"
              }
            }
          }
        },
        "OPERATION_PERMISSION_DENIED": {
          "description": "A well-formed request was performed however, the client did not meet the security conditions required to access the protected resource, therefore it is not possible to process the request.",
          "raised_by": "IPC Bus / Remote Protocol Adapter",
          "content": {
            "application/json": {
              "example": "{\"Header\": {\"Name\": \"OPERATION_PERMISSION_DENIED\", \"Description\": \"Unable to process the request because user \\u2018Admin\\u2019 does not have access privileges to invoke the \\u2018Set\\u2019 procedure on object \\u2018prpl.Dummy\\u2019.\"}}",
              "schema": {
                "$ref": "#/components/schemas/Response"
              }
            }
          }
        },
        "OPERATION_TIMEOUT": {
          "description": "A well-formed request was performed however, it was not possible to process the response within the allowed time-frame.",
          "raised_by": "Micro-Service",
          "content": {
            "application/json": {
              "example": "{\"Header\": {\"Name\": \"OPERATION_TIMEOUT\", \"Description\": \"The operation has been aborted because the service did not respond within the expected 5 seconds time-frame.\"}}",
              "schema": {
                "$ref": "#/components/schemas/Response"
              }
            }
          }
        }
      },
      "parameters": [
        {
          "in": "path",
          "name": "ButtonId",
          "type": "integer",
          "required": true,
          "description": "ID of a(n) Button",
          "schema": {
            "type": "integer",
            "format": "int32",
            "default": 20,
            "example": {
              "Limit": 10
            }
          }
        }
      ]
    },
    "System.Buttons.{ButtonId}.ResetStatistics": {
      "operationId": "System.Buttons.{ButtonId}.ResetStatistics",
      "summary": "Resets the statistics counters of the specified Button.",
      "tags": [
        "System.Buttons.{ButtonId}"
      ],
      "responses": {
        "ARGUMENT_DATA_TYPE_MISMATCH": {
          "description": "A call attempt to a valid object and procedure was performed, however an argument value was provided with an unexpected data type, therefore it was not possible to process the request.",
          "raised_by": "Micro-Service",
          "content": {
            "application/json": {
              "example": "{\"Header\": {\"Name\": \"ARGUMENT_DATA_TYPE_MISMATCH\", \"Description\": \"Unable to process the request because the value provided on the \\u2018Enabled\\u2019 field is not a valid Boolean.\"}}",
              "schema": {
                "$ref": "#/components/schemas/Response"
              }
            }
          }
        },
        "ARGUMENT_NOT_FOUND": {
          "description": "A call to a valid object and procedure was performed, however an unrecognized argument was provided, therefore it was not possible to process the request.",
          "raised_by": "Micro-Service",
          "content": {
            "application/json": {
              "example": "{\"Header\": {\"Name\": \"ARGUMENT_NOT_FOUND\", \"Description\": \"Unable to process the request because 'Enabled' is not a valid argument.\"}}",
              "schema": {
                "$ref": "#/components/schemas/Response"
              }
            }
          }
        },
        "ARGUMENT_REQUIRED_MISSING": {
          "description": "A call to a valid object and procedure was performed, however a required argument was not provided, therefore it was not possible to process the request.",
          "raised_by": "Micro-Service",
          "content": {
            "application/json": {
              "example": "{\"Header\": {\"Name\": \"ARGUMENT_REQUIRED_MISSING\", \"Description\": \"Unable to process the request because the 'Enabled' field was not provided.\"}}",
              "schema": {
                "$ref": "#/components/schemas/Response"
              }
            }
          }
        },
        "ARGUMENT_VALUE_NOT_SUPPORTED": {
          "description": "A call attempt to a valid object and procedure was performed, however a non-supported argument value was provided, therefore it was not possible to process the request.",
          "raised_by": "Micro-Service",
          "content": {
            "application/json": {
              "example": "{\"Header\": {\"Name\": \"ARGUMENT_VALUE_NOT_SUPPORTED\", \"Description\": \"Unable to process the request because \\u2018Red\\u2019 is not a value supported by the \\u2018Colour\\u2019 field.\"}}",
              "schema": {
                "$ref": "#/components/schemas/Response"
              }
            }
          }
        },
        "METHOD_NOT_FOUND": {
          "description": "A call to a valid object but non-existing procedure was performed, therefore it was not possible to process the request.",
          "raised_by": "IPC Bus",
          "content": {
            "application/json": {
              "example": "{\"Header\": {\"Name\": \"METHOD_NOT_FOUND\", \"Description\": \"Unable to process the request because 'Set' is not a valid method\"}}",
              "schema": {
                "$ref": "#/components/schemas/Response"
              }
            }
          }
        },
        "OBJECT_NOT_FOUND": {
          "description": "A call to a non-existing object was performed, therefore it was not possible to process the request.",
          "raised_by": "IPC Bus",
          "content": {
            "application/json": {
              "example": "{\"Header\": {\"Name\": \"OBJECT_NOT_FOUND\", \"Description\": \"Unable to process the request because 'prpl.Dummy' is not a valid object.\"}}",
              "schema": {
                "$ref": "#/components/schemas/Response"
              }
            }
          }
        },
        "OK": {
          "description": "A well-formed request to an authorized resource was performed, and the receiver was able to compute the response within the allowed time-window.",
          "raised_by": "Micro-Service",
          "content": {
            "application/json": {
              "example": "{\"Header\": {\"Name\": \"OK\"}}",
              "schema": {
                "allOf": [
                  {
                    "$ref": "#/components/schemas/Response"
                  },
                  {
                    "properties": {
                      "Body": {
                        "properties": {},
                        "required": []
                      }
                    }
                  }
                ]
              }
            }
          }
        },
        "OPERATION_ALREADY_IN_PROGRESS": {
          "description": "A well-formed request to an authorized resource was performed, however the operation could not be completed, as the required resource was temporarily locked by a different request in progress.",
          "raised_by": "Micro-Service",
          "content": {
            "application/json": {
              "example": "{\"Header\": {\"Name\": \"OPERATION_ALREADY_IN_PROGRESS\", \"Description\": \"Unable to process the request because there is a duplicate operation currently in progress.\"}}",
              "schema": {
                "$ref": "#/components/schemas/Response"
              }
            }
          }
        },
        "OPERATION_ERROR": {
          "description": "A well-formed request was performed however, it was not possible to process the request due to an unknown internal error.",
          "raised_by": "Micro-Service",
          "content": {
            "application/json": {
              "example": "{\"Header\": {\"Name\": \"OPERATION_ERROR\", \"Description\": \"Unable to process the request because there is a configuration error.\"}}",
              "schema": {
                "$ref": "#/components/schemas/Response"
              }
            }
          }
        },
        "OPERATION_ILLEGAL": {
          "description": "A well-formed request to an authorized resource was performed, however the operation could not be completed, as it was invoked in the incorrect system state or order.",
          "raised_by": "Micro-Service",
          "content": {
            "application/json": {
              "example": "{\"Header\": {\"Name\": \"OPERATION_ILLEGAL\", \"Description\": \"Unable to process the request because the 'Stop' procedure can only be invoked after the 'Start' method has been called.\"}}",
              "schema": {
                "$ref": "#/components/schemas/Response"
              }
            }
          }
        },
        "OPERATION_PERMISSION_DENIED": {
          "description": "A well-formed request was performed however, the client did not meet the security conditions required to access the protected resource, therefore it is not possible to process the request.",
          "raised_by": "IPC Bus / Remote Protocol Adapter",
          "content": {
            "application/json": {
              "example": "{\"Header\": {\"Name\": \"OPERATION_PERMISSION_DENIED\", \"Description\": \"Unable to process the request because user \\u2018Admin\\u2019 does not have access privileges to invoke the \\u2018Set\\u2019 procedure on object \\u2018prpl.Dummy\\u2019.\"}}",
              "schema": {
                "$ref": "#/components/schemas/Response"
              }
            }
          }
        },
        "OPERATION_TIMEOUT": {
          "description": "A well-formed request was performed however, it was not possible to process the response within the allowed time-frame.",
          "raised_by": "Micro-Service",
          "content": {
            "application/json": {
              "example": "{\"Header\": {\"Name\": \"OPERATION_TIMEOUT\", \"Description\": \"The operation has been aborted because the service did not respond within the expected 5 seconds time-frame.\"}}",
              "schema": {
                "$ref": "#/components/schemas/Response"
              }
            }
          }
        }
      },
      "requestBody": {
        "content": {
          "application/json": {
            "schema": {
              "properties": {},
              "required": []
            },
            "example": ""
          }
        }
      },
      "parameters": [
        {
          "in": "path",
          "name": "ButtonId",
          "type": "integer",
          "required": true,
          "description": "ID of a(n) Button",
          "schema": {
            "type": "integer",
            "format": "int32",
            "default": 20,
            "example": {
              "Limit": 10
            }
          }
        }
      ]
    },
    "System.Buttons.{ButtonId}.Set": {
      "operationId": "System.Buttons.{ButtonId}.Set",
      "summary": "Modifies the status and configuration parameters of the specified Button.",
      "tags": [
        "System.Buttons.{ButtonId}"
      ],
      "responses": {
        "ARGUMENT_DATA_TYPE_MISMATCH": {
          "description": "A call attempt to a valid object and procedure was performed, however an argument value was provided with an unexpected data type, therefore it was not possible to process the request.",
          "raised_by": "Micro-Service",
          "content": {
            "application/json": {
              "example": "{\"Header\": {\"Name\": \"ARGUMENT_DATA_TYPE_MISMATCH\", \"Description\": \"Unable to process the request because the value provided on the \\u2018Enabled\\u2019 field is not a valid Boolean.\"}}",
              "schema": {
                "$ref": "#/components/schemas/Response"
              }
            }
          }
        },
        "ARGUMENT_NOT_FOUND": {
          "description": "A call to a valid object and procedure was performed, however an unrecognized argument was provided, therefore it was not possible to process the request.",
          "raised_by": "Micro-Service",
          "content": {
            "application/json": {
              "example": "{\"Header\": {\"Name\": \"ARGUMENT_NOT_FOUND\", \"Description\": \"Unable to process the request because 'Enabled' is not a valid argument.\"}}",
              "schema": {
                "$ref": "#/components/schemas/Response"
              }
            }
          }
        },
        "ARGUMENT_REQUIRED_MISSING": {
          "description": "A call to a valid object and procedure was performed, however a required argument was not provided, therefore it was not possible to process the request.",
          "raised_by": "Micro-Service",
          "content": {
            "application/json": {
              "example": "{\"Header\": {\"Name\": \"ARGUMENT_REQUIRED_MISSING\", \"Description\": \"Unable to process the request because the 'Enabled' field was not provided.\"}}",
              "schema": {
                "$ref": "#/components/schemas/Response"
              }
            }
          }
        },
        "ARGUMENT_VALUE_NOT_SUPPORTED": {
          "description": "A call attempt to a valid object and procedure was performed, however a non-supported argument value was provided, therefore it was not possible to process the request.",
          "raised_by": "Micro-Service",
          "content": {
            "application/json": {
              "example": "{\"Header\": {\"Name\": \"ARGUMENT_VALUE_NOT_SUPPORTED\", \"Description\": \"Unable to process the request because \\u2018Red\\u2019 is not a value supported by the \\u2018Colour\\u2019 field.\"}}",
              "schema": {
                "$ref": "#/components/schemas/Response"
              }
            }
          }
        },
        "METHOD_NOT_FOUND": {
          "description": "A call to a valid object but non-existing procedure was performed, therefore it was not possible to process the request.",
          "raised_by": "IPC Bus",
          "content": {
            "application/json": {
              "example": "{\"Header\": {\"Name\": \"METHOD_NOT_FOUND\", \"Description\": \"Unable to process the request because 'Set' is not a valid method\"}}",
              "schema": {
                "$ref": "#/components/schemas/Response"
              }
            }
          }
        },
        "OBJECT_NOT_FOUND": {
          "description": "A call to a non-existing object was performed, therefore it was not possible to process the request.",
          "raised_by": "IPC Bus",
          "content": {
            "application/json": {
              "example": "{\"Header\": {\"Name\": \"OBJECT_NOT_FOUND\", \"Description\": \"Unable to process the request because 'prpl.Dummy' is not a valid object.\"}}",
              "schema": {
                "$ref": "#/components/schemas/Response"
              }
            }
          }
        },
        "OK": {
          "description": "A well-formed request to an authorized resource was performed, and the receiver was able to compute the response within the allowed time-window.",
          "raised_by": "Micro-Service",
          "content": {
            "application/json": {
              "example": "{\"Header\": {\"Name\": \"OK\"}}",
              "schema": {
                "allOf": [
                  {
                    "$ref": "#/components/schemas/Response"
                  },
                  {
                    "properties": {
                      "Body": {
                        "properties": {},
                        "required": []
                      }
                    }
                  }
                ]
              }
            }
          }
        },
        "OPERATION_ALREADY_IN_PROGRESS": {
          "description": "A well-formed request to an authorized resource was performed, however the operation could not be completed, as the required resource was temporarily locked by a different request in progress.",
          "raised_by": "Micro-Service",
          "content": {
            "application/json": {
              "example": "{\"Header\": {\"Name\": \"OPERATION_ALREADY_IN_PROGRESS\", \"Description\": \"Unable to process the request because there is a duplicate operation currently in progress.\"}}",
              "schema": {
                "$ref": "#/components/schemas/Response"
              }
            }
          }
        },
        "OPERATION_ERROR": {
          "description": "A well-formed request was performed however, it was not possible to process the request due to an unknown internal error.",
          "raised_by": "Micro-Service",
          "content": {
            "application/json": {
              "example": "{\"Header\": {\"Name\": \"OPERATION_ERROR\", \"Description\": \"Unable to process the request because there is a configuration error.\"}}",
              "schema": {
                "$ref": "#/components/schemas/Response"
              }
            }
          }
        },
        "OPERATION_ILLEGAL": {
          "description": "A well-formed request to an authorized resource was performed, however the operation could not be completed, as it was invoked in the incorrect system state or order.",
          "raised_by": "Micro-Service",
          "content": {
            "application/json": {
              "example": "{\"Header\": {\"Name\": \"OPERATION_ILLEGAL\", \"Description\": \"Unable to process the request because the 'Stop' procedure can only be invoked after the 'Start' method has been called.\"}}",
              "schema": {
                "$ref": "#/components/schemas/Response"
              }
            }
          }
        },
        "OPERATION_PERMISSION_DENIED": {
          "description": "A well-formed request was performed however, the client did not meet the security conditions required to access the protected resource, therefore it is not possible to process the request.",
          "raised_by": "IPC Bus / Remote Protocol Adapter",
          "content": {
            "application/json": {
              "example": "{\"Header\": {\"Name\": \"OPERATION_PERMISSION_DENIED\", \"Description\": \"Unable to process the request because user \\u2018Admin\\u2019 does not have access privileges to invoke the \\u2018Set\\u2019 procedure on object \\u2018prpl.Dummy\\u2019.\"}}",
              "schema": {
                "$ref": "#/components/schemas/Response"
              }
            }
          }
        },
        "OPERATION_TIMEOUT": {
          "description": "A well-formed request was performed however, it was not possible to process the response within the allowed time-frame.",
          "raised_by": "Micro-Service",
          "content": {
            "application/json": {
              "example": "{\"Header\": {\"Name\": \"OPERATION_TIMEOUT\", \"Description\": \"The operation has been aborted because the service did not respond within the expected 5 seconds time-frame.\"}}",
              "schema": {
                "$ref": "#/components/schemas/Response"
              }
            }
          }
        }
      },
      "requestBody": {
        "content": {
          "application/json": {
            "schema": {
              "properties": {
                "Actions": {
                  "type": "object",
                  "properties": {
                    "Click": {
                      "type": "object",
                      "properties": {
                        "Arguments": {
                          "type": "String",
                          "description": "Button click linked object arguments.",
                          "format": "-",
                          "default_value": "the existing configuration",
                          "possible_values": "\"null\" or valid JSON object",
                          "writeOnly": true
                        },
                        "Method": {
                          "type": "String",
                          "description": "Button click linked object method.",
                          "format": "-",
                          "default_value": "the existing configuration",
                          "possible_values": "valid object procedure",
                          "writeOnly": true
                        },
                        "Object": {
                          "type": "String",
                          "description": "Button click linked object.",
                          "format": "-",
                          "default_value": "the existing configuration",
                          "possible_values": "valid object",
                          "writeOnly": true
                        }
                      },
                      "required": []
                    },
                    "Press": {
                      "type": "object",
                      "properties": {
                        "Arguments": {
                          "type": "String",
                          "description": "Button press linked object arguments.",
                          "format": "-",
                          "default_value": "the existing configuration",
                          "possible_values": "\"null\" or valid JSON object",
                          "writeOnly": true
                        },
                        "Method": {
                          "type": "String",
                          "description": "Button press linked object method.",
                          "format": "-",
                          "default_value": "the existing configuration",
                          "possible_values": "valid object procedure",
                          "writeOnly": true
                        },
                        "Object": {
                          "type": "String",
                          "description": "Button press linked object.",
                          "format": "-",
                          "default_value": "the existing configuration",
                          "possible_values": "valid object",
                          "writeOnly": true
                        }
                      },
                      "required": []
                    }
                  },
                  "required": []
                },
                "Enabled": {
                  "type": "Boolean",
                  "description": "Button administrative status.",
                  "format": "-",
                  "default_value": "the existing configuration",
                  "possible_values": "\"true\" or \"false\"",
                  "enum": [
                    "true",
                    "false"
                  ],
                  "writeOnly": true
                },
                "Id": {
                  "type": "String",
                  "description": "Button unique identifier.",
                  "format": "1 up to 64 chars",
                  "default_value": "the existing configuration",
                  "possible_values": "any string with length from 1 up to 64 chars",
                  "writeOnly": true
                },
                "Name": {
                  "type": "String",
                  "description": "Button name (alias).",
                  "format": "-",
                  "default_value": "the existing configuration",
                  "possible_values": "any string with length from 1 up to 64 chars",
                  "writeOnly": true
                }
              },
              "required": []
            },
            "example": "{\"Id\": \"0\", \"Name\": \"Wi-Fi\", \"Enabled\": true, \"Actions\": {\"Click\": {\"Object\": \"Interfaces.Physical.Network.LAN.Wi-Fi.Radios.24GHz\", \"Method\": \"Set\", \"Arguments\": \"{\\\"Enabled\\\":false}\"}, \"Press\": {\"Object\": \"Services.Local.Wi-Fi.WPS.Pairing\", \"Method\": \"Start\", \"Arguments\": \"{}\"}}}"
          }
        }
      },
      "parameters": [
        {
          "in": "path",
          "name": "ButtonId",
          "type": "integer",
          "required": true,
          "description": "ID of a(n) Button",
          "schema": {
            "type": "integer",
            "format": "int32",
            "default": 20,
            "example": {
              "Limit": 10
            }
          }
        }
      ]
    }
  },
  "components": {
    "schemas": {
      "ListRequest": {
        "properties": {
          "Limit": {
            "description": "How many items to return at one time (max 200)",
            "required": false,
            "type": "integer",
            "schema": {
              "type": "integer",
              "format": "int32",
              "default": 20,
              "example": {
                "Limit": 10
              }
            }
          },
          "Offset": {
            "description": "Which object index to start with",
            "required": false,
            "type": "integer",
            "schema": {
              "type": "integer",
              "format": "int32",
              "default": 0,
              "example": {
                "Offset": 45
              }
            }
          }
        }
      },
      "Response": {
        "type": "object",
        "description": "schema for a responses to object methods",
        "oneOf": [
          {
            "properties": {
              "Header": {
                "type": "object",
                "description": "Header object specifying the name of the response type and providing a detailed description in case of an error",
                "properties": {
                  "Name": {
                    "type": "string",
                    "description": "name of the response type",
                    "enum": [
                      "OK"
                    ]
                  }
                },
                "required": [
                  "Name"
                ],
                "additionalProperties": false
              },
              "Body": {
                "type": "object"
              }
            },
            "additionalProperties": false
          },
          {
            "properties": {
              "Header": {
                "type": "object",
                "description": "Header object specifying the name of the response type and providing a detailed description in case of an error",
                "properties": {
                  "Name": {
                    "type": "string",
                    "description": "name of the response type",
                    "enum": [
                      "ARGUMENT_VALUE_NOT_SUPPORTED",
                      "OPERATION_ERROR",
                      "OPERATION_PERMISSION_DENIED",
                      "OPERATION_ILLEGAL",
                      "ARGUMENT_REQUIRED_MISSING",
                      "ARGUMENT_DATA_TYPE_MISMATCH",
                      "METHOD_NOT_FOUND",
                      "OPERATION_TIMEOUT",
                      "OPERATION_ALREADY_IN_PROGRESS",
                      "OBJECT_NOT_FOUND",
                      "OK",
                      "ARGUMENT_NOT_FOUND"
                    ]
                  },
                  "Description": {
                    "type": "string",
                    "description": "A more detailed error message. NOTE: only filled in when the operation returns an error."
                  }
                },
                "required": [
                  "Name",
                  "Description"
                ],
                "additionalProperties": false
              }
            },
            "additionalProperties": false
          }
        ]
      },
      "System.Buttons": {
        "description": "System.Buttons Object",
        "id": "System.Buttons",
        "type": "object",
        "required": [],
        "properties": {
          "Actions": {
            "type": "object",
            "properties": {
              "Click": {
                "type": "object",
                "properties": {
                  "Arguments": {
                    "type": "String",
                    "description": "Button click linked object arguments.",
                    "format": "-",
                    "default_value": "-",
                    "possible_values": "\"null\" or valid JSON object"
                  },
                  "Method": {
                    "type": "String",
                    "description": "Button click linked object method.",
                    "format": "-",
                    "default_value": "-",
                    "possible_values": "valid object procedure"
                  },
                  "Object": {
                    "type": "String",
                    "description": "Button click linked object.",
                    "format": "-",
                    "default_value": "-",
                    "possible_values": "valid object"
                  }
                },
                "required": []
              },
              "Press": {
                "type": "object",
                "properties": {
                  "Arguments": {
                    "type": "String",
                    "description": "Button press linked object arguments.",
                    "format": "-",
                    "default_value": "-",
                    "possible_values": "\"null\" or valid JSON object"
                  },
                  "Method": {
                    "type": "String",
                    "description": "Button press linked object method.",
                    "format": "-",
                    "default_value": "-",
                    "possible_values": "valid object procedure"
                  },
                  "Object": {
                    "type": "String",
                    "description": "Button press linked object.",
                    "format": "-",
                    "default_value": "-",
                    "possible_values": "valid object"
                  }
                },
                "required": []
              }
            },
            "required": []
          },
          "Enabled": {
            "type": "Boolean",
            "description": "Button administrative status.",
            "format": "-",
            "default_value": "-",
            "possible_values": "\"true\" or \"false\"",
            "enum": [
              "true",
              "false"
            ]
          },
          "Id": {
            "type": "String",
            "description": "Button unique identifier.",
            "format": "1 up to 64 chars",
            "default_value": "-",
            "possible_values": "any string with length from 1 up to 64 chars"
          },
          "Name": {
            "type": "String",
            "description": "Button name (alias).",
            "format": "-",
            "default_value": "-",
            "possible_values": "any string with length from 1 up to 64 chars"
          },
          "Statistics": {
            "type": "object",
            "properties": {
              "Click": {
                "type": "Integer",
                "description": "Button click count.",
                "format": "-",
                "default_value": "-",
                "possible_values": ">= 0",
                "readOnly": true
              },
              "Press": {
                "type": "Integer",
                "description": "Button press count.",
                "format": "-",
                "default_value": "-",
                "possible_values": ">= 0",
                "readOnly": true
              }
            },
            "required": []
          }
        },
        "events": {
          "SYSTEM_BUTTONS_CLICKED": {
            "content": {
              "application/json": {
                "example": "{\"ButtonId\": \"System.Buttons.0\"}"
              }
            },
            "description": "Raised when a Button is clicked.",
            "code": 1
          },
          "SYSTEM_BUTTONS_PRESSED": {
            "content": {
              "application/json": {
                "example": "{\"ButtonId\": \"System.Buttons.0\"}"
              }
            },
            "description": "Raised when a Button is pressed.",
            "code": 2
          }
        },
        "example": {},
        "layer": 4
      }
    }
  },
  "instances": {
    "WPS": {
      "description": "Physical WPS button."
    },
    "Wi-Fi": {
      "description": "Physical Wi-Fi button."
    }
  }
}